Workbook

Sheet Assumptions
A1: Scenario Control | B1: Base | XFD1: Base
XFD2: Upside
A3: Volume Assumption | J3: Volume breakup | P3: Driver | Q3: Upside Adj | R3: Downside Adj | XFD3: Downside
A4: Items | B4: 26 | C4: =B4+1 -> 27 | D4: =C4+1 -> 28 | E4: =D4+1 -> 29 | F4: =E4+1 -> 30 | J4: Items | K4: Value | P4: Volume Growth | Q4: 0.03 | R4: -0.03
A5: Domestic Growth % | B5: 0.07 | C5: 0.065 | D5: 0.06 | E5: 0.055 | F5: 0.05 | J5: Domestic % | K5: 0.85 | L5: Based on historical trends | P5: ASP Growth | Q5: 0.015 | R5: -0.015
A6: Export Growth % | B6: 0.1 | C6: 0.09 | D6: 0.08 | E6: 0.07 | F6: 0.06 | J6: Export % | K6: 0.15 | L6: Based on historical trends | P6: Raw Material % | Q6: -0.02 | R6: 0.02
P7: Employee Cost % | Q7: -0.005 | R7: 0.005
A8: Pricing Assumptions | J8: Export cars often cheaper | P8: Other Expenses % | Q8: -0.01 | R8: 0.01
A9: Item | B9: 26 | C9: =B9+1 -> 27 | D9: =C9+1 -> 28 | E9: =D9+1 -> 29 | F9: =E9+1 -> 30 | J9: Item | K9: Value | P9: Receivable Days | Q9: -3 | R9: 4
A10: Domestic ASP Growth % | B10: 0.05 | C10: 0.045 | D10: 0.04 | E10: 0.035 | F10: 0.03 | J10: Export ASP Discount % | K10: 0.1 | P10: Inventory Days | Q10: -3 | R10: 5
A11: Export ASP Growth % | B11: 0.04 | C11: 0.035 | D11: 0.03 | E11: 0.03 | F11: 0.03 | P11: Payable Days | Q11: 4 | R11: -4
A13: Cost Assumption
A14: Item | B14: 26 | C14: =B14+1 -> 27 | D14: =C14+1 -> 28 | E14: =D14+1 -> 29 | F14: =E14+1 -> 30
A15: Raw material % of sales | B15: 0.73 | C15: 0.725 | D15: 0.72 | E15: 0.715 | F15: 0.71
A16: Employee Cost % | B16: 0.05 | C16: 0.049 | D16: 0.048 | E16: 0.047 | F16: 0.046
A17: Other Expenses % | B17: 0.1 | C17: 0.098 | D17: 0.097 | E17: 0.096 | F17: 0.095
A19: Working Capital
A20: Item | B20: Value
A21: Receivable Days | B21: 20 | C21: Based on typical B2C trend of maruti and might extend period to remain competitive
A22: Inventory Days | B22: 30 | C22: Industry benchmark
A23: Payable Days | B23: 45 | C23: Assumed to stabalize strong relations with supplier etc.
A25: Item | B25: Value
A26: Depreciation % | B26: 0.03
A27: Interest % | B27: 0.005
A28: Tax % (of PBT) | B28: 0.25 | C28: Historical trend
A29: Other Income | B29: 0.03
A30: Capex % | B30: 0.04
A31: Dividend % (of PAT) | B31: 0.25

Sheet Historical
G2: Rs. In crores
B3: Year | C3: FY 21 | D3: FY 22 | E3: FY 23 | F3: FY 24 | G3: FY 25
B4: Revenue | C4: 70372 | D4: 88330 | E4: 117571 | F4: 141858 | G4: 152913
B5: EBITDA | C5: 5411 | D5: 5752 | E5: 11029 | F5: 18626 | G5: 20224
B6: EBITDA % | C6: =C5/C4 -> 0.076891377 | D6: =D5/D4 -> 0.065119438 | E6: =E5/E4 -> 0.093807146 | F6: =F5/F4 -> 0.13130031 | G6: =G5/G4 -> 0.13225821
B7: PAT | C7: 4389 | D7: 3880 | E7: 8211 | F7: 13488 | G7: 14500
B8: Volume (Unit Sold) | C8: 1457861 | D8: 1652653 | E8: 1966164 | F8: 2135323 | G8: 2234266
B9: Other Income | C9: 3046 | D9: 1861 | E9: 2307 | F9: 4248 | G9: 5199
B10: Other Income % | C10: =C9/C4 -> 0.043284261 | D10: =D9/D4 -> 0.02106872 | E10: =E9/E4 -> 0.019622186 | F10: =F9/F4 -> 0.029945438 | G10: =G9/G4 -> 0.033999725

Sheet Revenue
C2: Rs. In Crores
B3: Particulars | C3: =Historical!G3 -> FY 25
B4: Total Volume | C4: =Historical!G8 -> 2234266
B5: Domestic Volume | C5: =C4*Assumptions!K5 -> 1899126.1
B6: Export Volume | C6: =C4*Assumptions!K6 -> 335139.9
B7: Revenue | C7: =Historical!G4 -> 152913
B8: ASP | C8: =C7/C4 -> 0.068439926
B9: Domestic ASP | C9: =C7/(Revenue!C5+Revenue!C6*(1-Assumptions!K10)) -> 0.069482159
B10: Export ASP | C10: =C9*(1-Assumptions!K10) -> 0.062533943
B11: Domestic Revenue | C11: =C9*C5 -> 131955.38
B12: Export Revenue | C12: =C6*C10 -> 20957.619
B13: Total Revenue Check | C13: =SUM(C11:C12) -> 152913
H14: Rs. In crores
B15: Particular | C15: 25 | D15: =C15+1 -> 26 | E15: =D15+1 -> 27 | F15: =E15+1 -> 28 | G15: =F15+1 -> 29 | H15: =G15+1 -> 30
B16: Domestic Volume | C16: =C5 -> 1899126.1 | D16: =C16*(1+IF(Assumptions!$B$1="Base",Assumptions!B5,IF(Assumptions!$B$1="Upside",Assumptions!B5+Assumptions!$Q$4,Assumptions!B5+Assumptions!$R$4))) -> 2032064.9 | E16: =D16*(1+IF(Assumptions!$B$1="Base",Assumptions!C5,IF(Assumptions!$B$1="Upside",Assumptions!C5+Assumptions!$Q$4,Assumptions!C5+Assumptions!$R$4))) -> 2164149.1 | F16: =E16*(1+IF(Assumptions!$B$1="Base",Assumptions!D5,IF(Assumptions!$B$1="Upside",Assumptions!D5+Assumptions!$Q$4,Assumptions!D5+Assumptions!$R$4))) -> 2293998.1 | G16: =F16*(1+IF(Assumptions!$B$1="Base",Assumptions!E5,IF(Assumptions!$B$1="Upside",Assumptions!E5+Assumptions!$Q$4,Assumptions!E5+Assumptions!$R$4))) -> 2420168 | H16: =G16*(1+IF(Assumptions!$B$1="Base",Assumptions!F5,IF(Assumptions!$B$1="Upside",Assumptions!F5+Assumptions!$Q$4,Assumptions!F5+Assumptions!$R$4))) -> 2541176.4
B17: Export Volume | C17: =C6 -> 335139.9 | D17: =C17*(1+IF(Assumptions!$B$1="Base",Assumptions!B6,IF(Assumptions!$B$1="Upside",Assumptions!B6+Assumptions!$Q$4,Assumptions!B6+Assumptions!$R$4))) -> 368653.89 | E17: =D17*(1+IF(Assumptions!$B$1="Base",Assumptions!C6,IF(Assumptions!$B$1="Upside",Assumptions!C6+Assumptions!$Q$4,Assumptions!C6+Assumptions!$R$4))) -> 401832.74 | F17: =E17*(1+IF(Assumptions!$B$1="Base",Assumptions!D6,IF(Assumptions!$B$1="Upside",Assumptions!D6+Assumptions!$Q$4,Assumptions!D6+Assumptions!$R$4))) -> 433979.36 | G17: =F17*(1+IF(Assumptions!$B$1="Base",Assumptions!E6,IF(Assumptions!$B$1="Upside",Assumptions!E6+Assumptions!$Q$4,Assumptions!E6+Assumptions!$R$4))) -> 464357.91 | H17: =G17*(1+IF(Assumptions!$B$1="Base",Assumptions!F6,IF(Assumptions!$B$1="Upside",Assumptions!F6+Assumptions!$Q$4,Assumptions!F6+Assumptions!$R$4))) -> 492219.39
B18: Total Volume | C18: =SUM(C16:C17) -> 2234266 | D18: =SUM(D16:D17) -> 2400718.8 | E18: =SUM(E16:E17) -> 2565981.9 | F18: =SUM(F16:F17) -> 2727977.5 | G18: =SUM(G16:G17) -> 2884525.9 | H18: =SUM(H16:H17) -> 3033395.8
B19: Total Growth % | D19: =D18/C18-1 -> 0.0745 | E19: =E18/D18-1 -> 0.068838995 | F19: =F18/E18-1 -> 0.063132 | G19: =G18/F18-1 -> 0.05738627 | H19: =H18/G18-1 -> 0.051609824
B20: Domestic ASP | C20: =C9 -> 0.069482159 | D20: =C20*(1+IF(Assumptions!$B$1="Base",Assumptions!B10,IF(Assumptions!$B$1="Upside",Assumptions!B10+Assumptions!$Q$4,Assumptions!B10+Assumptions!$R$4))) -> 0.072956266 | E20: =D20*(1+IF(Assumptions!$B$1="Base",Assumptions!C10,IF(Assumptions!$B$1="Upside",Assumptions!C10+Assumptions!$Q$4,Assumptions!C10+Assumptions!$R$4))) -> 0.076239298 | F20: =E20*(1+IF(Assumptions!$B$1="Base",Assumptions!D10,IF(Assumptions!$B$1="Upside",Assumptions!D10+Assumptions!$Q$4,Assumptions!D10+Assumptions!$R$4))) -> 0.07928887 | G20: =F20*(1+IF(Assumptions!$B$1="Base",Assumptions!E10,IF(Assumptions!$B$1="Upside",Assumptions!E10+Assumptions!$Q$4,Assumptions!E10+Assumptions!$R$4))) -> 0.082063981 | H20: =G20*(1+IF(Assumptions!$B$1="Base",Assumptions!F10,IF(Assumptions!$B$1="Upside",Assumptions!F10+Assumptions!$Q$4,Assumptions!F10+Assumptions!$R$4))) -> 0.0845259
B21: Export ASP | C21: =C10 -> 0.062533943 | D21: =C21*(1+IF(Assumptions!$B$1="Base",Assumptions!B11,IF(Assumptions!$B$1="Upside",Assumptions!B11+Assumptions!$Q$4,Assumptions!B11+Assumptions!$R$4))) -> 0.0650353 | E21: =D21*(1+IF(Assumptions!$B$1="Base",Assumptions!C11,IF(Assumptions!$B$1="Upside",Assumptions!C11+Assumptions!$Q$4,Assumptions!C11+Assumptions!$R$4))) -> 0.067311536 | F21: =E21*(1+IF(Assumptions!$B$1="Base",Assumptions!D11,IF(Assumptions!$B$1="Upside",Assumptions!D11+Assumptions!$Q$4,Assumptions!D11+Assumptions!$R$4))) -> 0.069330882 | G21: =F21*(1+IF(Assumptions!$B$1="Base",Assumptions!E11,IF(Assumptions!$B$1="Upside",Assumptions!E11+Assumptions!$Q$4,Assumptions!E11+Assumptions!$R$4))) -> 0.071410808 | H21: =G21*(1+IF(Assumptions!$B$1="Base",Assumptions!F11,IF(Assumptions!$B$1="Upside",Assumptions!F11+Assumptions!$Q$4,Assumptions!F11+Assumptions!$R$4))) -> 0.073553133
B22: Domestic Revenue | C22: =C11 -> 131955.38 | D22: =D16*D20 -> 148251.87 | E22: =E16*E20 -> 164993.21 | F22: =F16*F20 -> 181888.52 | G22: =G16*G20 -> 198608.62 | H22: =H16*H20 -> 214795.22
B23: Export Revenue | C23: =C12 -> 20957.619 | D23: =D17*D21 -> 23975.516 | E23: =E17*E21 -> 27047.979 | F23: =F17*F21 -> 30088.172 | G23: =G17*G21 -> 33160.174 | H23: =H17*H21 -> 36204.278
B24: Total Revenue | C24: =C22+C23 -> 152913 | D24: =D22+D23 -> 172227.39 | E24: =E22+E23 -> 192041.19 | F24: =F22+F23 -> 211976.69 | G24: =G22+G23 -> 231768.79 | H24: =H22+H23 -> 250999.5

Sheet Cost
H1: Rs. In crores
B2: Particulars | C2: 25 | D2: =C2+1 -> 26 | E2: =D2+1 -> 27 | F2: =E2+1 -> 28 | G2: =F2+1 -> 29 | H2: =G2+1 -> 30
B3: Reveune | C3: =Revenue!C24 -> 152913 | D3: =Revenue!D24 -> 172227.39 | E3: =Revenue!E24 -> 192041.19 | F3: =Revenue!F24 -> 211976.69 | G3: =Revenue!G24 -> 231768.79 | H3: =Revenue!H24 -> 250999.5
B4: Raw Material cost | C4: =C3*70% -> 107039.1 | D4: =D3*IF(Assumptions!$B$1="Base",Assumptions!B15,IF(Assumptions!$B$1="Upside",Assumptions!B15+Assumptions!$Q$6,Assumptions!B15+Assumptions!$R$6)) -> 125725.99 | E4: =E3*IF(Assumptions!$B$1="Base",Assumptions!C15,IF(Assumptions!$B$1="Upside",Assumptions!C15+Assumptions!$Q$6,Assumptions!C15+Assumptions!$R$6)) -> 139229.86 | F4: =F3*IF(Assumptions!$B$1="Base",Assumptions!D15,IF(Assumptions!$B$1="Upside",Assumptions!D15+Assumptions!$Q$6,Assumptions!D15+Assumptions!$R$6)) -> 152623.22 | G4: =G3*IF(Assumptions!$B$1="Base",Assumptions!E15,IF(Assumptions!$B$1="Upside",Assumptions!E15+Assumptions!$Q$6,Assumptions!E15+Assumptions!$R$6)) -> 165714.69 | H4: =H3*IF(Assumptions!$B$1="Base",Assumptions!F15,IF(Assumptions!$B$1="Upside",Assumptions!F15+Assumptions!$Q$6,Assumptions!F15+Assumptions!$R$6)) -> 178209.65
B5: Employee cost | C5: =C3*5% -> 7645.65 | D5: =D4*IF(Assumptions!$B$1="Base",Assumptions!B16,IF(Assumptions!$B$1="Upside",Assumptions!B16+Assumptions!$Q$6,Assumptions!B16+Assumptions!$R$6)) -> 6286.2996 | E5: =E4*IF(Assumptions!$B$1="Base",Assumptions!C16,IF(Assumptions!$B$1="Upside",Assumptions!C16+Assumptions!$Q$6,Assumptions!C16+Assumptions!$R$6)) -> 6822.2633 | F5: =F4*IF(Assumptions!$B$1="Base",Assumptions!D16,IF(Assumptions!$B$1="Upside",Assumptions!D16+Assumptions!$Q$6,Assumptions!D16+Assumptions!$R$6)) -> 7325.9144 | G5: =G4*IF(Assumptions!$B$1="Base",Assumptions!E16,IF(Assumptions!$B$1="Upside",Assumptions!E16+Assumptions!$Q$6,Assumptions!E16+Assumptions!$R$6)) -> 7788.5903 | H5: =H4*IF(Assumptions!$B$1="Base",Assumptions!F16,IF(Assumptions!$B$1="Upside",Assumptions!F16+Assumptions!$Q$6,Assumptions!F16+Assumptions!$R$6)) -> 8197.6437
B6: Other Expenses | C6: 18004.25 | D6: =D5*IF(Assumptions!$B$1="Base",Assumptions!B17,IF(Assumptions!$B$1="Upside",Assumptions!B17+Assumptions!$Q$6,Assumptions!B17+Assumptions!$R$6)) -> 628.62996 | E6: =E5*IF(Assumptions!$B$1="Base",Assumptions!C17,IF(Assumptions!$B$1="Upside",Assumptions!C17+Assumptions!$Q$6,Assumptions!C17+Assumptions!$R$6)) -> 668.58181 | F6: =F5*IF(Assumptions!$B$1="Base",Assumptions!D17,IF(Assumptions!$B$1="Upside",Assumptions!D17+Assumptions!$Q$6,Assumptions!D17+Assumptions!$R$6)) -> 710.6137 | G6: =G5*IF(Assumptions!$B$1="Base",Assumptions!E17,IF(Assumptions!$B$1="Upside",Assumptions!E17+Assumptions!$Q$6,Assumptions!E17+Assumptions!$R$6)) -> 747.70467 | H6: =H5*IF(Assumptions!$B$1="Base",Assumptions!F17,IF(Assumptions!$B$1="Upside",Assumptions!F17+Assumptions!$Q$6,Assumptions!F17+Assumptions!$R$6)) -> 778.77615
B7: Total Cost | C7: =SUM(C4:C6) -> 132689 | D7: =SUM(D4:D6) -> 132640.92 | E7: =SUM(E4:E6) -> 146720.71 | F7: =SUM(F4:F6) -> 160659.74 | G7: =SUM(G4:G6) -> 174250.98 | H7: =SUM(H4:H6) -> 187186.06

Sheet P&L
H1: Rs. In crores
B2: Particulars | C2: 25 | D2: =C2+1 -> 26 | E2: =D2+1 -> 27 | F2: =E2+1 -> 28 | G2: =F2+1 -> 29 | H2: =G2+1 -> 30
B3: Reveune | C3: =Revenue!C24 -> 152913 | D3: =Revenue!D24 -> 172227.39 | E3: =Revenue!E24 -> 192041.19 | F3: =Revenue!F24 -> 211976.69 | G3: =Revenue!G24 -> 231768.79 | H3: =Revenue!H24 -> 250999.5
B4: Raw Material cost | C4: =Cost!C4 -> 107039.1 | D4: =Cost!D4 -> 125725.99 | E4: =Cost!E4 -> 139229.86 | F4: =Cost!F4 -> 152623.22 | G4: =Cost!G4 -> 165714.69 | H4: =Cost!H4 -> 178209.65
B5: Employee cost | C5: =Cost!C5 -> 7645.65 | D5: =Cost!D5 -> 6286.2996 | E5: =Cost!E5 -> 6822.2633 | F5: =Cost!F5 -> 7325.9144 | G5: =Cost!G5 -> 7788.5903 | H5: =Cost!H5 -> 8197.6437
B6: Other Expenses | C6: =Cost!C6 -> 18004.25 | D6: =Cost!D6 -> 628.62996 | E6: =Cost!E6 -> 668.58181 | F6: =Cost!F6 -> 710.6137 | G6: =Cost!G6 -> 747.70467 | H6: =Cost!H6 -> 778.77615
B7: EBITDA | C7: =C3-SUM(C4:C6) -> 20224 | D7: =D3-SUM(D4:D6) -> 39586.465 | E7: =E3-SUM(E4:E6) -> 45320.483 | F7: =F3-SUM(F4:F6) -> 51316.945 | G7: =G3-SUM(G4:G6) -> 57517.811 | H7: =H3-SUM(H4:H6) -> 63813.435
B8: EBITDA % | C8: =C7/C3 -> 0.13225821 | D8: =D7/D3 -> 0.22985 | E8: =E7/E3 -> 0.23599355 | F8: =F7/F3 -> 0.24208768 | G8: =G7/G3 -> 0.24816892 | H8: =H7/H3 -> 0.2542373
B9: Depreciation | C9: 5608 | D9: =D3*Assumptions!$B$26 -> 5166.8216 | E9: =E3*Assumptions!$B$26 -> 5761.2357 | F9: =F3*Assumptions!$B$26 -> 6359.3007 | G9: =G3*Assumptions!$B$26 -> 6953.0638 | H9: =H3*Assumptions!$B$26 -> 7529.985
B10: EBIT | C10: =C7-C9 -> 14616 | D10: =D7-D9 -> 34419.643 | E10: =E7-E9 -> 39559.247 | F10: =F7-F9 -> 44957.644 | G10: =G7-G9 -> 50564.747 | H10: =H7-H9 -> 56283.45
B11: Other Income | C11: 5199 | D11: =D3*Assumptions!$B$29 -> 5166.8216 | E11: =E3*Assumptions!$B$29 -> 5761.2357 | F11: =F3*Assumptions!$B$29 -> 6359.3007 | G11: =G3*Assumptions!$B$29 -> 6953.0638 | H11: =H3*Assumptions!$B$29 -> 7529.985
B12: Interest | C12: 194 | D12: =D3*Assumptions!$B$27 -> 861.13693 | E12: =E3*Assumptions!$B$27 -> 960.20596 | F12: =F3*Assumptions!$B$27 -> 1059.8834 | G12: =G3*Assumptions!$B$27 -> 1158.844 | H12: =H3*Assumptions!$B$27 -> 1254.9975
B13: PBT | C13: =C10+C11-C12 -> 19621 | D13: =D10+D11-D12 -> 38725.328 | E13: =E10+E11-E12 -> 44360.277 | F13: =F10+F11-F12 -> 50257.061 | G13: =G10+G11-G12 -> 56358.967 | H13: =H10+H11-H12 -> 62558.438
B14: Tax | C14: =C13*26% -> 5101.46 | D14: =D13*Assumptions!$B$28 -> 9681.332 | E14: =E13*Assumptions!$B$28 -> 11090.069 | F14: =F13*Assumptions!$B$28 -> 12564.265 | G14: =G13*Assumptions!$B$28 -> 14089.742 | H14: =H13*Assumptions!$B$28 -> 15639.609
B15: PAT | C15: =C13-C14 -> 14519.54 | D15: =D13-D14 -> 29043.996 | E15: =E13-E14 -> 33270.207 | F15: =F13-F14 -> 37692.796 | G15: =G13-G14 -> 42269.225 | H15: =H13-H14 -> 46918.828

Sheet working capital
H1: Rs. In crores
B2: Particular | C2: 25 | D2: =C2+1 -> 26 | E2: =D2+1 -> 27 | F2: =E2+1 -> 28 | G2: =F2+1 -> 29 | H2: =G2+1 -> 30
B3: Revenue | C3: ='P&L'!C3 -> 152913 | D3: ='P&L'!D3 -> 172227.39 | E3: ='P&L'!E3 -> 192041.19 | F3: ='P&L'!F3 -> 211976.69 | G3: ='P&L'!G3 -> 231768.79 | H3: ='P&L'!H3 -> 250999.5
B4: Receivables | C4: 6540 | D4: =D$3*IF(Assumptions!$B$1="Base",Assumptions!$B$21,IF(Assumptions!$B$1="Upside",Assumptions!$B$21+Assumptions!$Q$9,Assumptions!$B$21+Assumptions!$R$9))/365 -> 9437.1171 | E4: =E$3*IF(Assumptions!$B$1="Base",Assumptions!$B$21,IF(Assumptions!$B$1="Upside",Assumptions!$B$21+Assumptions!$Q$9,Assumptions!$B$21+Assumptions!$R$9))/365 -> 10522.805 | F4: =F$3*IF(Assumptions!$B$1="Base",Assumptions!$B$21,IF(Assumptions!$B$1="Upside",Assumptions!$B$21+Assumptions!$Q$9,Assumptions!$B$21+Assumptions!$R$9))/365 -> 11615.161 | G4: =G$3*IF(Assumptions!$B$1="Base",Assumptions!$B$21,IF(Assumptions!$B$1="Upside",Assumptions!$B$21+Assumptions!$Q$9,Assumptions!$B$21+Assumptions!$R$9))/365 -> 12699.66 | H4: =H$3*IF(Assumptions!$B$1="Base",Assumptions!$B$21,IF(Assumptions!$B$1="Upside",Assumptions!$B$21+Assumptions!$Q$9,Assumptions!$B$21+Assumptions!$R$9))/365 -> 13753.397
B5: Inventory | C5: 6913 | D5: =D$3*IF(Assumptions!$B$1="Base",Assumptions!$B$22,IF(Assumptions!$B$1="Upside",Assumptions!$B$22+Assumptions!$Q$9,Assumptions!$B$22+Assumptions!$R$9))/365 -> 14155.676 | E5: =E$3*IF(Assumptions!$B$1="Base",Assumptions!$B$22,IF(Assumptions!$B$1="Upside",Assumptions!$B$22+Assumptions!$Q$9,Assumptions!$B$22+Assumptions!$R$9))/365 -> 15784.208 | F5: =F$3*IF(Assumptions!$B$1="Base",Assumptions!$B$22,IF(Assumptions!$B$1="Upside",Assumptions!$B$22+Assumptions!$Q$9,Assumptions!$B$22+Assumptions!$R$9))/365 -> 17422.742 | G5: =G$3*IF(Assumptions!$B$1="Base",Assumptions!$B$22,IF(Assumptions!$B$1="Upside",Assumptions!$B$22+Assumptions!$Q$9,Assumptions!$B$22+Assumptions!$R$9))/365 -> 19049.49 | H5: =H$3*IF(Assumptions!$B$1="Base",Assumptions!$B$22,IF(Assumptions!$B$1="Upside",Assumptions!$B$22+Assumptions!$Q$9,Assumptions!$B$22+Assumptions!$R$9))/365 -> 20630.096
B6: Payables | C6: 20502 | D6: =D$3*IF(Assumptions!$B$1="Base",Assumptions!$B$23,IF(Assumptions!$B$1="Upside",Assumptions!$B$23+Assumptions!$Q$9,Assumptions!$B$23+Assumptions!$R$9))/365 -> 21233.513 | E6: =E$3*IF(Assumptions!$B$1="Base",Assumptions!$B$23,IF(Assumptions!$B$1="Upside",Assumptions!$B$23+Assumptions!$Q$9,Assumptions!$B$23+Assumptions!$R$9))/365 -> 23676.311 | F6: =F$3*IF(Assumptions!$B$1="Base",Assumptions!$B$23,IF(Assumptions!$B$1="Upside",Assumptions!$B$23+Assumptions!$Q$9,Assumptions!$B$23+Assumptions!$R$9))/365 -> 26134.112 | G6: =G$3*IF(Assumptions!$B$1="Base",Assumptions!$B$23,IF(Assumptions!$B$1="Upside",Assumptions!$B$23+Assumptions!$Q$9,Assumptions!$B$23+Assumptions!$R$9))/365 -> 28574.235 | H6: =H$3*IF(Assumptions!$B$1="Base",Assumptions!$B$23,IF(Assumptions!$B$1="Upside",Assumptions!$B$23+Assumptions!$Q$9,Assumptions!$B$23+Assumptions!$R$9))/365 -> 30945.144
B7: Net working Capital (NWC) | C7: =C4+C5-C6 -> -7049 | D7: =D4+D5-D6 -> 2359.2793 | E7: =E4+E5-E6 -> 2630.7013 | F7: =F4+F5-F6 -> 2903.7903 | G7: =G4+G5-G6 -> 3174.915 | H7: =H4+H5-H6 -> 3438.3493
B8: Change in NWC | C8: -378 | D8: =D7-C7 -> 9408.2793 | E8: =E7-D7 -> 271.42198 | F8: =F7-E7 -> 273.08901 | G8: =G7-F7 -> 271.12472 | H8: =H7-G7 -> 263.43434

Sheet cash flow
H1: Rs. In crores
B2: Particulars | C2: 25 | D2: =C2+1 -> 26 | E2: =D2+1 -> 27 | F2: =E2+1 -> 28 | G2: =F2+1 -> 29 | H2: =G2+1 -> 30
B3: PAT | C3: ='P&L'!C15 -> 14519.54 | D3: ='P&L'!D15 -> 29043.996 | E3: ='P&L'!E15 -> 33270.207 | F3: ='P&L'!F15 -> 37692.796 | G3: ='P&L'!G15 -> 42269.225 | H3: ='P&L'!H15 -> 46918.828
B4: + Depreciation | C4: ='P&L'!C9 -> 5608 | D4: ='P&L'!D9 -> 5166.8216 | E4: ='P&L'!E9 -> 5761.2357 | F4: ='P&L'!F9 -> 6359.3007 | G4: ='P&L'!G9 -> 6953.0638 | H4: ='P&L'!H9 -> 7529.985
B5: Change in NWC | C5: {='working capital'!C8:H8} -> -378 | D5: 9408.2793 | E5: 271.42198 | F5: 273.08901 | G5: 271.12472 | H5: 263.43434
B6: Cash Flow from Operations (CFO) | C6: =C3+C4-C5 -> 20505.54 | D6: =D3+D4-D5 -> 24802.538 | E6: =E3+E4-E5 -> 38760.021 | F6: =F3+F4-F5 -> 43779.008 | G6: =G3+G4-G5 -> 48951.165 | H6: =H3+H4-H5 -> 54185.379
B7: - Capex | C7: 34961.54 | D7: ='P&L'!D3*Assumptions!$B$30 -> 6889.0955 | E7: ='P&L'!E3*Assumptions!$B$30 -> 7681.6477 | F7: ='P&L'!F3*Assumptions!$B$30 -> 8479.0676 | G7: ='P&L'!G3*Assumptions!$B$30 -> 9270.7517 | H7: ='P&L'!H3*Assumptions!$B$30 -> 10039.98
B8: Cash Flow from Investing (CFI) | C8: =C6-C7 -> -14456 | D8: =D6-D7 -> 17913.443 | E8: =E6-E7 -> 31078.374 | F8: =F6-F7 -> 35299.94 | G8: =G6-G7 -> 39680.413 | H8: =H6-H7 -> 44145.399
B9: Dividend | C9: 3930 | D9: =D3*Assumptions!$B$31 -> 7260.999 | E9: =E3*Assumptions!$B$31 -> 8317.5519 | F9: =F3*Assumptions!$B$31 -> 9423.199 | G9: =G3*Assumptions!$B$31 -> 10567.306 | H9: =H3*Assumptions!$B$31 -> 11729.707
B10: Net Cash Flow | C10: =C8-C9 -> -18386 | D10: =D8-D9 -> 10652.444 | E10: =E8-E9 -> 22760.822 | F10: =F8-F9 -> 25876.741 | G10: =G8-G9 -> 29113.106 | H10: =H8-H9 -> 32415.692

Sheet Dashboard
A1: Key Metrics
A3: Metric | B3: 25 | C3: 30
A4: Revenue | B4: ='P&L'!C3 -> 152913 | C4: ='P&L'!H3 -> 250999.5
A5: EBITDA | B5: ='P&L'!C7 -> 20224 | C5: ='P&L'!H7 -> 63813.435
A6: EBITDA % | B6: ='P&L'!C8 -> 0.13225821 | C6: ='P&L'!H8 -> 0.2542373
A7: PAT | B7: ='P&L'!C15 -> 14519.54 | C7: ='P&L'!H15 -> 46918.828
A9: Metric | B9: Value
A10: Revenue CAGR | B10: =(C4/B4)^(1/5)-1 -> 0.10419478
A11: EBITDA CAGR | B11: =(C5/B5)^(1/5)-1 -> 0.25837191
A12: PAT CAGR | B12: =(C6/B6)^(1/5)-1 -> 0.13962856
